subconscious/__init__.py
subconscious/client.py
subconscious/errors.py
subconscious/types.py
subconscious_sdk-0.2.0.dist-info/licenses/LICENSE
subconscious_sdk-0.2.0.dist-info/METADATA
subconscious_sdk-0.2.0.dist-info/WHEEL
subconscious_sdk-0.2.0.dist-info/top_level.txt
subconscious_sdk-0.2.0.dist-info/RECORD
