Metadata-Version: 2.4
Name: subconscious-sdk
Version: 0.2.0
Summary: The official Python SDK for the Subconscious API
Author-email: Hongyin Luo <hongyin@subconscious.dev>, Jack O'Brien <jack@subconscious.dev>
License: Apache-2.0
Project-URL: Homepage, https://subconscious.dev
Project-URL: Documentation, https://docs.subconscious.dev
Project-URL: Repository, https://github.com/subconscious-systems/subconscious-python
Project-URL: Issues, https://github.com/subconscious-systems/subconscious-python/issues
Keywords: ai,agent,api,sdk,subconscious
Classifier: Development Status :: 4 - Beta
Classifier: Intended Audience :: Developers
Classifier: Programming Language :: Python :: 3
Classifier: Programming Language :: Python :: 3.8
Classifier: Programming Language :: Python :: 3.9
Classifier: Programming Language :: Python :: 3.10
Classifier: Programming Language :: Python :: 3.11
Classifier: Programming Language :: Python :: 3.12
Classifier: Topic :: Software Development :: Libraries :: Python Modules
Classifier: Topic :: Scientific/Engineering :: Artificial Intelligence
Requires-Python: >=3.8
License-File: LICENSE
Requires-Dist: requests>=2.25.0
Provides-Extra: dev
Requires-Dist: pytest>=7.0.0; extra == "dev"
Requires-Dist: pytest-cov>=4.0.0; extra == "dev"
Requires-Dist: black>=22.0.0; extra == "dev"
Requires-Dist: isort>=5.0.0; extra == "dev"
Requires-Dist: mypy>=1.0.0; extra == "dev"
Requires-Dist: types-requests>=2.28.0; extra == "dev"
Dynamic: license-file
